LICENSE
MANIFEST.in
README.md
setup.py
django_theherk_resources.egg-info/PKG-INFO
django_theherk_resources.egg-info/SOURCES.txt
django_theherk_resources.egg-info/dependency_links.txt
django_theherk_resources.egg-info/requires.txt
django_theherk_resources.egg-info/top_level.txt
resources/__init__.py
resources/admin/__init__.py
resources/admin/organizations.py
resources/admin/people.py
resources/cms_plugins/__init__.py
resources/cms_plugins/organization.py
resources/cms_plugins/organization_and_people.py
resources/cms_plugins/people.py
resources/migrations/0001_initial.py
resources/migrations/__init__.py
resources/models/__init__.py
resources/models/contact_types.py
resources/models/organizations.py
resources/models/people.py
resources/templates/resources/cms_plugins/organization.html
resources/templates/resources/cms_plugins/organization_and_people.html
resources/templates/resources/cms_plugins/people.html