Metadata-Version: 1.1
Name: django-theherk-resources
Version: 1.5
Summary: Django app for keeping data on organizations and people.
Home-page: https://github.com/theherk/django-theherk-resources
Author: Adam Sherwood
Author-email: theherk@gmail.com
License: see file LICENSE
Download-URL: https://github.com/theherk/django-theherk-resources/archive/1.5.zip
Platform: UNKNOWN
Classifier: Environment :: Web Environment
Classifier: Framework :: Django
Classifier: Intended Audience :: Developers
Classifier: Operating System :: OS Independent
Classifier: Programming Language :: Python
Classifier: Programming Language :: Python :: 2.6
Classifier: Programming Language :: Python :: 2.7
Classifier: Topic :: Internet :: WWW/HTTP
Classifier: Topic :: Internet :: WWW/HTTP :: Dynamic Content
